highchartexport/__init__.py
highchartexport/__main__.py
highchartexport-0.0.5.dist-info/LICENSE
highchartexport-0.0.5.dist-info/METADATA
highchartexport-0.0.5.dist-info/WHEEL
highchartexport-0.0.5.dist-info/entry_points.txt
highchartexport-0.0.5.dist-info/top_level.txt
highchartexport-0.0.5.dist-info/RECORD
